packagetime/__init__.py
packagetime/main.py
packagetime-4.0.0.dist-info/DESCRIPTION.rst
packagetime-4.0.0.dist-info/METADATA
packagetime-4.0.0.dist-info/RECORD
packagetime-4.0.0.dist-info/WHEEL
packagetime-4.0.0.dist-info/entry_points.txt
packagetime-4.0.0.dist-info/metadata.json
packagetime-4.0.0.dist-info/top_level.txt
