Metadata-Version: 2.0
Name: packagetime
Version: 4.0.0
Summary: commit and publish packages
Home-page: UNKNOWN
Author: Yoav Kleinberger
Author-email: haarcuba@gmail.com
License: UNKNOWN
Platform: UNKNOWN
Classifier: Programming Language :: Python
Requires-Dist: PyYAML
Provides-Extra: testing
